proj00/baek.py
proj00/bmi.py
proj00/test1.py
proj00/test2.py
proj00-0.0.0.9.dist-info/METADATA
proj00-0.0.0.9.dist-info/WHEEL
proj00-0.0.0.9.dist-info/top_level.txt
proj00-0.0.0.9.dist-info/RECORD
