Metadata-Version: 2.1
Name: proj00
Version: 0.0.0.9
Summary: proj00 강의용 프로젝트
Home-page: UNKNOWN
Author: 신누리
Author-email: nr8122@gmail.com
License: MIT
Platform: UNKNOWN
Requires-Python: >=3
